protecto_ai/__init__.py
protecto_ai/protecto_privacy_vault/__init__.py
protecto_ai/protecto_privacy_vault/vault_operations.py
protecto_ai-1.0.2.dist-info/METADATA
protecto_ai-1.0.2.dist-info/WHEEL
protecto_ai-1.0.2.dist-info/top_level.txt
protecto_ai-1.0.2.dist-info/RECORD
