Metadata-Version: 2.1
Name: protecto_ai
Version: 1.0.2
Summary: Intelligent Data Tokenization for Enhanced Privacy and Security
Author-email: Protecto <developer@protecto.ai>
License: MIT
Project-URL: Homepage, https://help.protecto.ai/tokenization-packages/
Project-URL: Documentation, https://developer.protecto.ai/docs/protecto-tokenization/
Project-URL: Website, https://www.protecto.ai/
Classifier: Programming Language :: Python :: 3.8
Classifier: License :: OSI Approved :: MIT License
Classifier: Operating System :: OS Independent
Requires-Python: >=3.8
Requires-Dist: requests ==2.26.0
Requires-Dist: multipledispatch ==1.0.0
